django_fabtasks-0.1.2.dist-info/DESCRIPTION.rst
django_fabtasks-0.1.2.dist-info/METADATA
django_fabtasks-0.1.2.dist-info/metadata.json
django_fabtasks-0.1.2.dist-info/pbr.json
django_fabtasks-0.1.2.dist-info/RECORD
django_fabtasks-0.1.2.dist-info/top_level.txt
django_fabtasks-0.1.2.dist-info/WHEEL
fabtasks/__init__.py
fabtasks/context.py
fabtasks/development/__init__.py
fabtasks/development/db.py
fabtasks/development/files.py
fabtasks/development/git.py
fabtasks/development/setup.py
fabtasks/production/__init__.py
fabtasks/production/db.py
fabtasks/production/files.py
fabtasks/production/git.py
fabtasks/production/services.py
fabtasks/production/setup.py
