Metadata-Version: 2.0
Name: django-fabtasks
Version: 0.1.2
Summary: Common Fabric tasks for use in Django development/deployments
Home-page: https://bitbucket.org/tsantor/django-fabtasks
Author: Tim Santor
Author-email: tsantor@xstudios.agency
License: MIT
Keywords: django-fabtasks
Platform: UNKNOWN
Classifier: Development Status :: 2 - Pre-Alpha
Classifier: Intended Audience :: Developers
Classifier: License :: OSI Approved :: BSD License
Classifier: Natural Language :: English
Classifier: Programming Language :: Python :: 2
Classifier: Programming Language :: Python :: 2.6
Classifier: Programming Language :: Python :: 2.7
Classifier: Programming Language :: Python :: 3
Classifier: Programming Language :: Python :: 3.3
Classifier: Programming Language :: Python :: 3.4
Requires-Dist: django-extensions
